iotPlatform/__init__.py
iotPlatform/util.py
iotPlatform-0.0.1.dist-info/METADATA
iotPlatform-0.0.1.dist-info/WHEEL
iotPlatform-0.0.1.dist-info/top_level.txt
iotPlatform-0.0.1.dist-info/RECORD
