Metadata-Version: 2.1
Name: iotPlatform
Version: 0.0.1
Summary: iotPlatform functions
Author: fdl
Author-email: 1316017498@qq.com
License: apache 3.0
Platform: UNKNOWN
Requires: json
Requires: requests
